creator/__init__.py
creator/copier.py
creator/main.py
creator/flask_app/.env.sample
creator/flask_app/.gitignore
creator/flask_app/Pipfile
creator/flask_app/README.md
creator/flask_app/config.py
creator/flask_app/main.py
creator/flask_app/manage.py
creator/flask_app/requirements.txt
creator/flask_app/api/__init__.py
creator/flask_app/api/datab.py
creator/flask_app/api/blueprints/__init__.py
creator/flask_app/api/blueprints/base_blueprint.py
creator/flask_app/api/blueprints/users.py
creator/flask_app/api/controllers/__init__.py
creator/flask_app/api/controllers/base_controller.py
creator/flask_app/api/controllers/user_controller.py
creator/flask_app/api/models/__init__.py
creator/flask_app/api/models/user.py
creator/flask_app/tests/__init__.py
creator/flask_app/tests/base_test.py
creator/flask_app/tests/test_hello_world.py
flask_app-1.0.1.dist-info/AUTHORS
flask_app-1.0.1.dist-info/LICENSE
flask_app-1.0.1.dist-info/METADATA
flask_app-1.0.1.dist-info/WHEEL
flask_app-1.0.1.dist-info/entry_points.txt
flask_app-1.0.1.dist-info/pbr.json
flask_app-1.0.1.dist-info/top_level.txt
flask_app-1.0.1.dist-info/RECORD
