Metadata-Version: 2.1
Name: flask-app
Version: 1.0.1
Summary: A tool to create flask boilerplate code
Home-page: https://github.com/kimbugp/flask_app
Author: Kimbugwe Simon Peter
Author-email: kimbsimon2@gmail.com
License: MIT
Project-URL: Source Code, https://github.com/kimbugp/flask_app
Platform: UNKNOWN
Classifier: Environment :: Console
Classifier: Environment :: OpenStack
Classifier: Intended Audience :: Developers
Classifier: Operating System :: OS Independent
Classifier: Programming Language :: Python :: 3
Classifier: License :: OSI Approved :: MIT License
